MANIFEST.in
setup.py
documentation/powerline.sql
powerline/__init__.py
powerline/database.py
powerline/json.py
powerline/main.py
powerline/manager.py
powerline/output.py
powerline/xmlrpc.py
powerline.egg-info/PKG-INFO
powerline.egg-info/SOURCES.txt
powerline.egg-info/dependency_links.txt
powerline.egg-info/not-zip-safe
powerline.egg-info/requires.txt
powerline.egg-info/top_level.txt
powerline/lib/__init__.py
powerline/lib/plugin.py
powerline/templates/dump.html
powerline/templates/index.html
powerline/templates/layout.html
powerline/templates/data/color.css
powerline/templates/data/humanmsg.css
powerline/templates/data/humanmsg.js
powerline/templates/data/jquery.js
powerline/templates/data/jquery.ui.datepicker.js
powerline/templates/data/layout.css
powerline/templates/data/manager.css
powerline/templates/data/reset.css
powerline/templates/data/sessionview.js
powerline/templates/data/images/done.png
powerline/templates/data/images/on.png
powerline/templates/data/images/waiting.png
powerline/templates/manager/hours.html
powerline/templates/manager/index.html
powerline/templates/manager/login-setup.html
powerline/templates/manager/login.html
powerline/templates/manager/session-log.html
powerline/templates/manager/settings.html
powerline/templates/manager/statistics.html
powerline/templates/manager/systems.html
powerline/templates/manager/user-search.html
powerline/templates/manager/user.html
powerline/templates/manager/users.html
powerline/tools/__init__.py
powerline/tools/client.py
powerline/tools/wsgi_server.py
