Metadata-Version: 1.0
Name: powerline
Version: 0.2.1
Summary: Simple computer reservations system
Home-page: http://code.google.com/p/powerline/
Author: Pianohacker
Author-email: pianohacker@gmail.com
License: GPLv3
Platform: UNKNOWN
